{
    "DNDConfig": null,
    "__parentReadjusting__": false,
    "_enabled_": false,
    "_height_": {
        "type": "ref",
        "value": "preferred"
    },
    "_left_": {
        "type": "string",
        "value": "0dp"
    },
    "_margin_": [
        1,
        1,
        1,
        1
    ],
    "_padding_": [
        0,
        0,
        0,
        0
    ],
    "_skin_": "s4ebab87a08740ebaa5f70685ec48ad2",
    "_text_": "Label",
    "_top_": {
        "type": "string",
        "value": "0dp"
    },
    "_width_": {
        "type": "ref",
        "value": "preferred"
    },
    "_wrapping_": 2,
    "canUpdateUI": true,
    "containerId": true,
    "containerweight": 100,
    "contentalignment": 4,
    "enabled": false,
    "id": "Label0bf978aa4152548",
    "info": null,
    "ipad": {
        "psp": {
            "wrapping": 2
        }
    },
    "iphone": {
        "@class": "com.kony.gen.viz.model.component.property.label.IPhoneLabelProperty",
        "psp": {
            "wrapping": 2
        }
    },
    "isSegmentChild": true,
    "isvisible": true,
    "kuid": "d635283a8ced43ed9948a4046b7ce31a",
    "name": "kony.ui.Label",
    "parent": "FlexContainer07ece49a0225b44",
    "pf": "CopyFBox0078d58a83bb442",
    "tooltip": "",
    "wType": "Label",
    "zindex": 1
}